tinystan/__init__.py
tinystan/__version.py
tinystan/compile.py
tinystan/download.py
tinystan/model.py
tinystan/output.py
tinystan/py.typed
tinystan/util.py
tinystan-0.3.2.dist-info/METADATA
tinystan-0.3.2.dist-info/WHEEL
tinystan-0.3.2.dist-info/top_level.txt
tinystan-0.3.2.dist-info/RECORD
