Metadata-Version: 2.4
Name: tinystan
Version: 0.3.2
Author-email: Brian Ward <bward@flatironinstitute.org>
License: BSD-3-Clause
Classifier: Programming Language :: Python :: 3
Classifier: Development Status :: 4 - Beta
Requires-Python: >=3.8
Requires-Dist: numpy
Requires-Dist: dllist~=2.0.0
Requires-Dist: stanio~=0.5.1
